{
    "name": "Clarity\\Providers\\Cache",
    "line": 19,
    "short_desc": "This provider manages the cache drivers",
    "long_desc": "",
    "hint": null,
    "tags": [],
    "namespace": "Clarity\\Providers",
    "file": "\/var\/www\/phalconslayer\/api\/..\/framework\/src\/Clarity\/Providers\/Cache.php",
    "relative_file": null,
    "hash": "b6fdf4e7c2d50f0cd78fdbd2f99e131326496d16",
    "parent": "Clarity\\Providers\\ServiceProvider",
    "modifiers": "Stmt_Class",
    "is_trait": false,
    "is_interface": false,
    "aliases": [],
    "errors": [],
    "interfaces": [],
    "traits": [],
    "properties": [],
    "methods": {
        "register": {
            "name": "register",
            "line": 44,
            "short_desc": "{@inheridoc}",
            "long_desc": "",
            "hint": [
                [
                    "mixed",
                    false
                ]
            ],
            "hint_desc": null,
            "tags": [],
            "modifiers": "1",
            "is_by_ref": "",
            "exceptions": [],
            "errors": [],
            "parameters": []
        }
    },
    "constants": []
}